{
  "instructors": [
    {
      "avatar_url": "https://source.unsplash.com/collection/3465564/500x500",
      "birth": 1593561600000,
      "created_at": 1593017096344,
      "id": 1,
      "name": "Adilson Souza e Silva Junior",
      "services": "sedentarismo",
      "gender": "F"
    },
    {
      "id": 2,
      "name": "Adilson Souza e Silva Junior",
      "avatar_url": "http://google.com",
      "birth": 1593043200000,
      "services": "sedentarismo, preguiça, cansaço",
      "gender": "M",
      "created_at": 1593017155320
    },
    {
      "id": 3,
      "name": "Adilson Souza e Silva Junior",
      "avatar_url": "http://google.com",
      "birth": 598406400000,
      "services": "sedentarismo",
      "gender": "M",
      "created_at": 1593022078895
    }
  ]
}